case/__init__.py
case/case.py
case/mock.py
case/pytest.py
case/skip.py
case/utils.py
case/tests/__init__.py
case-1.5.3.dist-info/DESCRIPTION.rst
case-1.5.3.dist-info/METADATA
case-1.5.3.dist-info/RECORD
case-1.5.3.dist-info/WHEEL
case-1.5.3.dist-info/entry_points.txt
case-1.5.3.dist-info/metadata.json
case-1.5.3.dist-info/top_level.txt
