Metadata-Version: 1.1
Name: case
Version: 1.5.3
Summary: Python unittest Utilities
Home-page: http://github.com/celery/case
Author: Ask Solem
Author-email: ask@celeryproject.org
License: BSD
Keywords: test unit testing pytest unittest mock patch
Platform: any
Classifier: Development Status :: 5 - Production/Stable
Classifier: Programming Language :: Python
Classifier: Programming Language :: Python :: 2
Classifier: Programming Language :: Python :: 2.7
Classifier: Programming Language :: Python :: 2.6
Classifier: Programming Language :: Python :: 3
Classifier: Programming Language :: Python :: 3.3
Classifier: Programming Language :: Python :: 3.4
Classifier: Programming Language :: Python :: 3.5
Classifier: License :: OSI Approved :: BSD License
Classifier: Intended Audience :: Developers
Classifier: Operating System :: OS Independent
